{"100_index.md":"B5Qe7JxI","101_index.md":"tTUhrE0u","102_index.md":"BRXBXc-t","103_index.md":"CxeS3dLx","200_index.md":"BpcBNHvY","201_index.md":"hjqDZoK6","202_index.md":"DI9jw8Yi","203_index.md":"DkykbHXN","204_index.md":"DTnhaoCw","205_index.md":"ChSBON0N","206_index.md":"DHP-DVEn","207_index.md":"D5B-1ZIJ","208_index.md":"nxkYzBcz","226_index.md":"DrofbeSq","300_index.md":"CAmdjFxF","301_index.md":"CDpbheQt","302_index.md":"DPim_PT8","303_index.md":"B_8hpg0-","304_index.md":"DDTUU7JA","305_index.md":"XIIVKWB7","306_index.md":"CdyL-rIP","307_index.md":"BXpv4oDt","308_index.md":"DIX17113","400_index.md":"D-sYCCON","401_index.md":"C6wet_yH","402_index.md":"D593Ewzc","403_index.md":"Cda2Bduq","404_index.md":"4gx6oBUD","405_index.md":"CRdfEwJG","406_index.md":"en_0wMzn","407_index.md":"NxeDi-ap","408_index.md":"COnA91MC","409_index.md":"BIavslyh","410_index.md":"BLdaLVfy","411_index.md":"BYoN0d-A","412_index.md":"kLcWg_Ss","413_index.md":"Btmcc4_p","414_index.md":"Db63wh3X","415_index.md":"B86HlbXT","416_index.md":"BAOaIHSi","417_index.md":"DkIN4JAp","418_index.md":"CFsdeCGe","421_index.md":"BTUeeMeO","422_index.md":"pT24LRBq","423_index.md":"DkISxW-q","424_index.md":"GEWZBPSz","425_index.md":"Cv4kXCkg","426_index.md":"DOhzJCSE","428_index.md":"DVMxpspw","429_index.md":"B7YVUh0L","431_index.md":"BCkIr6Vx","451_index.md":"BG-iX5yV","500_index.md":"DaijIrKX","501_index.md":"DHtPI8uv","502_index.md":"BX4e54Jl","503_index.md":"n1XPpERQ","504_index.md":"8m_3kitR","505_index.md":"D26Z9pOx","506_index.md":"CA0tO1Bg","507_index.md":"Co81m_Sr","508_index.md":"ADPAgxIh","510_index.md":"bqD44FtH","511_index.md":"BPpVLTLI","en_about_index.md":"DVSiPWcJ","en_blog_index.md":"C-TNWjXW","en_docs_index.md":"CzqpsdQ8","en_index.md":"CeNJ6R8w","en_project_index.md":"CQNEpAso","en_snowfox_changelog_index.md":"B0s4f35x","en_snowfox_index.md":"fdUNObcc","en_snowfox_manual_index.md":"DQbYsO7g","index.md":"BIMANxGQ","zh_about_index.md":"D8qaxXm2","zh_blog_index.md":"Dzwro1l7","zh_docs_index.md":"Bvd3vnKe","zh_index.md":"CnuUjElM","zh_project_index.md":"BwHPE52d","zh_snowfox_changelog_index.md":"DkaDEJSN","zh_snowfox_index.md":"Bgh8yCG3","zh_snowfox_manual_index.md":"fsUZF5CA","zhou_pr_index.md":"C694hJEJ"}
